LICENSE
MANIFEST.in
README.md
pyproject.toml
fgslpyrest/fgslpyrest.py
fgslpyrest.egg-info/PKG-INFO
fgslpyrest.egg-info/SOURCES.txt
fgslpyrest.egg-info/dependency_links.txt
fgslpyrest.egg-info/top_level.txt
fgslpyrest/http/.gitignore
fgslpyrest/http/Rest.py
fgslpyrest/http/__init__.py
fgslpyrest/http/resttest.py