Metadata-Version: 2.1
Name: fgslpyrest
Version: 1.1.0
Summary: A class to make HTTP REST requests
Author-email: Flávio Gomes da Silva Lisboa <flavio.lisboa@fgsl.eti.br>
Project-URL: Homepage, https://github.com/fgsl/fgslpyrest
Project-URL: Documentation, https://github.com/fgsl/fgslpyrest
Project-URL: Repository, https://github.com/fgsl/fgslpyrest
Classifier: Programming Language :: Python :: 3
Classifier: License :: OSI Approved :: MIT License
Classifier: Operating System :: OS Independent
Requires-Python: >=3.10
License-File: LICENSE
